{
  "period": {
    "start": "2025-07-14T16:23:14.349Z",
    "end": "2025-07-15T16:23:14.349Z",
    "duration": "24 hours"
  },
  "summary": {
    "totalRequests": 0,
    "successfulRequests": 0,
    "errorCount": 0,
    "successRate": 100,
    "avgResponseTime": 0,
    "uptime": 0.00003935185185185185,
    "memoryUsage": 45.240485024884464,
    "timestamp": "2025-07-15T16:23:14.352Z"
  },
  "requests": {
    "total": 0,
    "byEndpoint": {},
    "topEndpoints": [],
    "slowestEndpoints": []
  },
  "errors": {
    "total": 0,
    "byType": {},
    "recent": [],
    "trend": "stable"
  },
  "performance": {},
  "alerts": [],
  "recommendations": []
}