{
  "period": {
    "start": "2025-07-11T13:08:46.358Z",
    "end": "2025-07-12T13:08:46.358Z",
    "duration": "24 hours"
  },
  "summary": {
    "totalRequests": 0,
    "successfulRequests": 0,
    "errorCount": 0,
    "successRate": 100,
    "avgResponseTime": 0,
    "uptime": 0.00005208333333333334,
    "memoryUsage": 44.45764142094695,
    "timestamp": "2025-07-12T13:08:46.359Z"
  },
  "requests": {
    "total": 0,
    "byEndpoint": {},
    "topEndpoints": [],
    "slowestEndpoints": []
  },
  "errors": {
    "total": 0,
    "byType": {},
    "recent": [],
    "trend": "stable"
  },
  "performance": {},
  "alerts": [],
  "recommendations": []
}